<?xml version="1.0" encoding="UTF-8" standalone="no"?><IndicadoresFinancieros xmlns:xsi="http://www.w3.org/2001/XMLSchema-instance" SchemaVersion="1.0" xsi:schemaLocation="http://api.sbif.cl http://api.sbif.cl/IndicadoresFinancieros-v1.0.xsd" xmlns="http://api.sbif.cl"><UFs/><UTMs/><TABs/><IPCs/><Dolares><Dolar><Fecha>2009-01-02</Fecha><Valor>636,45</Valor></Dolar><Dolar><Fecha>2009-01-05</Fecha><Valor>640,91</Valor></Dolar><Dolar><Fecha>2009-01-06</Fecha><Valor>643,87</Valor></Dolar><Dolar><Fecha>2009-01-07</Fecha><Valor>497,93</Valor></Dolar><Dolar><Fecha>2009-01-08</Fecha><Valor>630,19</Valor></Dolar><Dolar><Fecha>2009-01-09</Fecha><Valor>629,5</Valor></Dolar><Dolar><Fecha>2009-01-12</Fecha><Valor>616,95</Valor></Dolar><Dolar><Fecha>2009-01-13</Fecha><Valor>610,09</Valor></Dolar><Dolar><Fecha>2009-01-14</Fecha><Valor>614,85</Valor></Dolar><Dolar><Fecha>2009-01-15</Fecha><Valor>615,85</Valor></Dolar><Dolar><Fecha>2009-01-16</Fecha><Valor>625,63</Valor></Dolar><Dolar><Fecha>2009-01-19</Fecha><Valor>615,48</Valor></Dolar><Dolar><Fecha>2009-01-20</Fecha><Valor>620,78</Valor></Dolar><Dolar><Fecha>2009-01-21</Fecha><Valor>624,81</Valor></Dolar><Dolar><Fecha>2009-01-22</Fecha><Valor>623,64</Valor></Dolar><Dolar><Fecha>2009-01-23</Fecha><Valor>622,3</Valor></Dolar><Dolar><Fecha>2009-01-26</Fecha><Valor>621,17</Valor></Dolar><Dolar><Fecha>2009-01-27</Fecha><Valor>616,94</Valor></Dolar><Dolar><Fecha>2009-01-28</Fecha><Valor>616,2</Valor></Dolar><Dolar><Fecha>2009-01-29</Fecha><Valor>611,89</Valor></Dolar><Dolar><Fecha>2009-01-30</Fecha><Valor>612,43</Valor></Dolar><Dolar><Fecha>2009-02-02</Fecha><Valor>617,1</Valor></Dolar><Dolar><Fecha>2009-02-03</Fecha><Valor>621,78</Valor></Dolar><Dolar><Fecha>2009-02-04</Fecha><Valor>623,87</Valor></Dolar><Dolar><Fecha>2009-02-05</Fecha><Valor>617,2</Valor></Dolar><Dolar><Fecha>2009-02-06</Fecha><Valor>620,28</Valor></Dolar><Dolar><Fecha>2009-02-09</Fecha><Valor>615,82</Valor></Dolar><Dolar><Fecha>2009-02-10</Fecha><Valor>610,13</Valor></Dolar><Dolar><Fecha>2009-02-11</Fecha><Valor>605,70</Valor></Dolar><Dolar><Fecha>2009-02-12</Fecha><Valor>602,12</Valor></Dolar><Dolar><Fecha>2009-02-13</Fecha><Valor>593,02</Valor></Dolar><Dolar><Fecha>2009-02-16</Fecha><Valor>583,32</Valor></Dolar><Dolar><Fecha>2009-02-17</Fecha><Valor>584,35</Valor></Dolar><Dolar><Fecha>2009-02-18</Fecha><Valor>592,37</Valor></Dolar><Dolar><Fecha>2009-02-19</Fecha><Valor>592,45</Valor></Dolar><Dolar><Fecha>2009-02-20</Fecha><Valor>604,17</Valor></Dolar><Dolar><Fecha>2009-02-23</Fecha><Valor>533,24</Valor></Dolar><Dolar><Fecha>2009-02-24</Fecha><Valor>621,41</Valor></Dolar><Dolar><Fecha>2009-02-25</Fecha><Valor>598,98</Valor></Dolar><Dolar><Fecha>2009-02-26</Fecha><Valor>600,69</Valor></Dolar><Dolar><Fecha>2009-02-27</Fecha><Valor>595,76</Valor></Dolar><Dolar><Fecha>2009-03-02</Fecha><Valor>599,04</Valor></Dolar><Dolar><Fecha>2009-03-03</Fecha><Valor>603,73</Valor></Dolar><Dolar><Fecha>2009-03-04</Fecha><Valor>609,29</Valor></Dolar><Dolar><Fecha>2009-03-05</Fecha><Valor>614,85</Valor></Dolar><Dolar><Fecha>2009-03-06</Fecha><Valor>610,79</Valor></Dolar><Dolar><Fecha>2009-03-09</Fecha><Valor>605,4</Valor></Dolar><Dolar><Fecha>2009-03-10</Fecha><Valor>610,18</Valor></Dolar><Dolar><Fecha>2009-03-11</Fecha><Valor>604,88</Valor></Dolar><Dolar><Fecha>2009-03-12</Fecha><Valor>601,47</Valor></Dolar><Dolar><Fecha>2009-03-13</Fecha><Valor>598,09</Valor></Dolar><Dolar><Fecha>2009-03-16</Fecha><Valor>594</Valor></Dolar><Dolar><Fecha>2009-03-17</Fecha><Valor>585,95</Valor></Dolar><Dolar><Fecha>2009-03-18</Fecha><Valor>583,29</Valor></Dolar><Dolar><Fecha>2009-03-19</Fecha><Valor>591,72</Valor></Dolar><Dolar><Fecha>2009-03-20</Fecha><Valor>584,24</Valor></Dolar><Dolar><Fecha>2009-03-23</Fecha><Valor>587,14</Valor></Dolar><Dolar><Fecha>2009-03-24</Fecha><Valor>579,78</Valor></Dolar><Dolar><Fecha>2009-03-25</Fecha><Valor>576,44</Valor></Dolar><Dolar><Fecha>2009-03-26</Fecha><Valor>574,47</Valor></Dolar><Dolar><Fecha>2009-03-27</Fecha><Valor>575,25</Valor></Dolar><Dolar><Fecha>2009-03-30</Fecha><Valor>572,39</Valor></Dolar><Dolar><Fecha>2009-03-31</Fecha><Valor>582,1</Valor></Dolar><Dolar><Fecha>2009-04-01</Fecha><Valor>583,26</Valor></Dolar><Dolar><Fecha>2009-04-02</Fecha><Valor>582,08</Valor></Dolar><Dolar><Fecha>2009-04-03</Fecha><Valor>575,12</Valor></Dolar><Dolar><Fecha>2009-04-06</Fecha><Valor>580,35</Valor></Dolar><Dolar><Fecha>2009-04-07</Fecha><Valor>582,2</Valor></Dolar><Dolar><Fecha>2009-04-08</Fecha><Valor>582,81</Valor></Dolar><Dolar><Fecha>2009-04-09</Fecha><Valor>580,61</Valor></Dolar><Dolar><Fecha>2009-04-13</Fecha><Valor>577,31</Valor></Dolar><Dolar><Fecha>2009-04-14</Fecha><Valor>577,8</Valor></Dolar><Dolar><Fecha>2009-04-15</Fecha><Valor>577,73</Valor></Dolar><Dolar><Fecha>2009-04-16</Fecha><Valor>579,34</Valor></Dolar><Dolar><Fecha>2009-04-17</Fecha><Valor>577,12</Valor></Dolar><Dolar><Fecha>2009-04-20</Fecha><Valor>578,66</Valor></Dolar><Dolar><Fecha>2009-04-21</Fecha><Valor>583,96</Valor></Dolar><Dolar><Fecha>2009-04-22</Fecha><Valor>583,13</Valor></Dolar><Dolar><Fecha>2009-04-23</Fecha><Valor>583,67</Valor></Dolar><Dolar><Fecha>2009-04-24</Fecha><Valor>584,23</Valor></Dolar><Dolar><Fecha>2009-04-27</Fecha><Valor>587,54</Valor></Dolar><Dolar><Fecha>2009-04-28</Fecha><Valor>600,11</Valor></Dolar><Dolar><Fecha>2009-04-29</Fecha><Valor>601,04</Valor></Dolar><Dolar><Fecha>2009-04-30</Fecha><Valor>588,62</Valor></Dolar><Dolar><Fecha>2009-05-04</Fecha><Valor>580,1</Valor></Dolar><Dolar><Fecha>2009-05-05</Fecha><Valor>573,55</Valor></Dolar><Dolar><Fecha>2009-05-06</Fecha><Valor>568,85</Valor></Dolar><Dolar><Fecha>2009-05-07</Fecha><Valor>571,12</Valor></Dolar><Dolar><Fecha>2009-05-08</Fecha><Valor>564,44</Valor></Dolar><Dolar><Fecha>2009-05-11</Fecha><Valor>562,53</Valor></Dolar><Dolar><Fecha>2009-05-12</Fecha><Valor>568,45</Valor></Dolar><Dolar><Fecha>2009-05-13</Fecha><Valor>568,09</Valor></Dolar><Dolar><Fecha>2009-05-14</Fecha><Valor>570,84</Valor></Dolar><Dolar><Fecha>2009-05-15</Fecha><Valor>564,2</Valor></Dolar><Dolar><Fecha>2009-05-18</Fecha><Valor>560,34</Valor></Dolar><Dolar><Fecha>2009-05-19</Fecha><Valor>559,11</Valor></Dolar><Dolar><Fecha>2009-05-20</Fecha><Valor>559,56</Valor></Dolar><Dolar><Fecha>2009-05-22</Fecha><Valor>558,95</Valor></Dolar><Dolar><Fecha>2009-05-25</Fecha><Valor>561,55</Valor></Dolar><Dolar><Fecha>2009-05-26</Fecha><Valor>562,39</Valor></Dolar><Dolar><Fecha>2009-05-27</Fecha><Valor>564,33</Valor></Dolar><Dolar><Fecha>2009-05-28</Fecha><Valor>565,6</Valor></Dolar><Dolar><Fecha>2009-05-29</Fecha><Valor>564,64</Valor></Dolar><Dolar><Fecha>2009-06-01</Fecha><Valor>560,58</Valor></Dolar><Dolar><Fecha>2009-06-02</Fecha><Valor>560,62</Valor></Dolar><Dolar><Fecha>2009-06-03</Fecha><Valor>562,52</Valor></Dolar><Dolar><Fecha>2009-06-04</Fecha><Valor>565,67</Valor></Dolar><Dolar><Fecha>2009-06-05</Fecha><Valor>566,12</Valor></Dolar><Dolar><Fecha>2009-06-08</Fecha><Valor>565,77</Valor></Dolar><Dolar><Fecha>2009-06-09</Fecha><Valor>568,71</Valor></Dolar><Dolar><Fecha>2009-06-10</Fecha><Valor>566,25</Valor></Dolar><Dolar><Fecha>2009-06-11</Fecha><Valor>565,62</Valor></Dolar><Dolar><Fecha>2009-06-12</Fecha><Valor>564,24</Valor></Dolar><Dolar><Fecha>2009-06-15</Fecha><Valor>562,09</Valor></Dolar><Dolar><Fecha>2009-06-16</Fecha><Valor>565,21</Valor></Dolar><Dolar><Fecha>2009-06-17</Fecha><Valor>553,14</Valor></Dolar><Dolar><Fecha>2009-06-18</Fecha><Valor>549,99</Valor></Dolar><Dolar><Fecha>2009-06-19</Fecha><Valor>539,81</Valor></Dolar><Dolar><Fecha>2009-06-22</Fecha><Valor>536,43</Valor></Dolar><Dolar><Fecha>2009-06-23</Fecha><Valor>534,42</Valor></Dolar><Dolar><Fecha>2009-06-24</Fecha><Valor>533,8</Valor></Dolar><Dolar><Fecha>2009-06-25</Fecha><Valor>532,69</Valor></Dolar><Dolar><Fecha>2009-06-26</Fecha><Valor>531,93</Valor></Dolar><Dolar><Fecha>2009-06-30</Fecha><Valor>529,07</Valor></Dolar><Dolar><Fecha>2009-07-01</Fecha><Valor>531,76</Valor></Dolar><Dolar><Fecha>2009-07-02</Fecha><Valor>534,99</Valor></Dolar><Dolar><Fecha>2009-07-03</Fecha><Valor>543,59</Valor></Dolar><Dolar><Fecha>2009-07-06</Fecha><Valor>541,37</Valor></Dolar><Dolar><Fecha>2009-07-07</Fecha><Valor>540,35</Valor></Dolar><Dolar><Fecha>2009-07-08</Fecha><Valor>540,42</Valor></Dolar><Dolar><Fecha>2009-07-09</Fecha><Valor>546,05</Valor></Dolar><Dolar><Fecha>2009-07-10</Fecha><Valor>547,65</Valor></Dolar><Dolar><Fecha>2009-07-13</Fecha><Valor>551,7</Valor></Dolar><Dolar><Fecha>2009-07-14</Fecha><Valor>548,68</Valor></Dolar><Dolar><Fecha>2009-07-15</Fecha><Valor>548,35</Valor></Dolar><Dolar><Fecha>2009-07-17</Fecha><Valor>541,3</Valor></Dolar><Dolar><Fecha>2009-07-20</Fecha><Valor>532,17</Valor></Dolar><Dolar><Fecha>2009-07-21</Fecha><Valor>531,33</Valor></Dolar><Dolar><Fecha>2009-07-22</Fecha><Valor>532,59</Valor></Dolar><Dolar><Fecha>2009-07-23</Fecha><Valor>533,61</Valor></Dolar><Dolar><Fecha>2009-07-24</Fecha><Valor>534,12</Valor></Dolar><Dolar><Fecha>2009-07-27</Fecha><Valor>538,22</Valor></Dolar><Dolar><Fecha>2009-07-28</Fecha><Valor>540,85</Valor></Dolar><Dolar><Fecha>2009-07-29</Fecha><Valor>544,72</Valor></Dolar><Dolar><Fecha>2009-07-30</Fecha><Valor>543,53</Valor></Dolar><Dolar><Fecha>2009-07-31</Fecha><Valor>541,9</Valor></Dolar><Dolar><Fecha>2009-08-03</Fecha><Valor>541,3</Valor></Dolar><Dolar><Fecha>2009-08-04</Fecha><Valor>538,22</Valor></Dolar><Dolar><Fecha>2009-08-05</Fecha><Valor>539,4</Valor></Dolar><Dolar><Fecha>2009-08-06</Fecha><Valor>540,99</Valor></Dolar><Dolar><Fecha>2009-08-07</Fecha><Valor>541,71</Valor></Dolar><Dolar><Fecha>2009-08-10</Fecha><Valor>542,98</Valor></Dolar><Dolar><Fecha>2009-08-11</Fecha><Valor>546,37</Valor></Dolar><Dolar><Fecha>2009-08-12</Fecha><Valor>549,79</Valor></Dolar><Dolar><Fecha>2009-08-13</Fecha><Valor>546,53</Valor></Dolar><Dolar><Fecha>2009-08-14</Fecha><Valor>545,36</Valor></Dolar><Dolar><Fecha>2009-08-17</Fecha><Valor>552,21</Valor></Dolar><Dolar><Fecha>2009-08-18</Fecha><Valor>558,71</Valor></Dolar><Dolar><Fecha>2009-08-19</Fecha><Valor>556,31</Valor></Dolar><Dolar><Fecha>2009-08-20</Fecha><Valor>552,65</Valor></Dolar><Dolar><Fecha>2009-08-21</Fecha><Valor>548,06</Valor></Dolar><Dolar><Fecha>2009-08-24</Fecha><Valor>543,50</Valor></Dolar><Dolar><Fecha>2009-08-25</Fecha><Valor>546,53</Valor></Dolar><Dolar><Fecha>2009-08-26</Fecha><Valor>546,19</Valor></Dolar><Dolar><Fecha>2009-08-27</Fecha><Valor>548,57</Valor></Dolar><Dolar><Fecha>2009-08-28</Fecha><Valor>548,55</Valor></Dolar><Dolar><Fecha>2009-08-31</Fecha><Valor>550,64</Valor></Dolar><Dolar><Fecha>2009-09-01</Fecha><Valor>550,36</Valor></Dolar><Dolar><Fecha>2009-09-02</Fecha><Valor>555,29</Valor></Dolar><Dolar><Fecha>2009-09-03</Fecha><Valor>557,74</Valor></Dolar><Dolar><Fecha>2009-09-04</Fecha><Valor>555,87</Valor></Dolar><Dolar><Fecha>2009-09-07</Fecha><Valor>552,42</Valor></Dolar><Dolar><Fecha>2009-09-08</Fecha><Valor>550,96</Valor></Dolar><Dolar><Fecha>2009-09-09</Fecha><Valor>551,87</Valor></Dolar><Dolar><Fecha>2009-09-10</Fecha><Valor>551,64</Valor></Dolar><Dolar><Fecha>2009-09-11</Fecha><Valor>554,03</Valor></Dolar><Dolar><Fecha>2009-09-14</Fecha><Valor>550,57</Valor></Dolar><Dolar><Fecha>2009-09-15</Fecha><Valor>551,88</Valor></Dolar><Dolar><Fecha>2009-09-16</Fecha><Valor>551,37</Valor></Dolar><Dolar><Fecha>2009-09-17</Fecha><Valor>545,72</Valor></Dolar><Dolar><Fecha>2009-09-21</Fecha><Valor>545,96</Valor></Dolar><Dolar><Fecha>2009-09-22</Fecha><Valor>544,50</Valor></Dolar><Dolar><Fecha>2009-09-23</Fecha><Valor>540,48</Valor></Dolar><Dolar><Fecha>2009-09-24</Fecha><Valor>539,71</Valor></Dolar><Dolar><Fecha>2009-09-25</Fecha><Valor>540,96</Valor></Dolar><Dolar><Fecha>2009-09-28</Fecha><Valor>544,66</Valor></Dolar><Dolar><Fecha>2009-09-29</Fecha><Valor>545,44</Valor></Dolar><Dolar><Fecha>2009-09-30</Fecha><Valor>546,07</Valor></Dolar><Dolar><Fecha>2009-10-01</Fecha><Valor>550,36</Valor></Dolar><Dolar><Fecha>2009-10-02</Fecha><Valor>553,30</Valor></Dolar><Dolar><Fecha>2009-10-05</Fecha><Valor>557,41</Valor></Dolar><Dolar><Fecha>2009-10-06</Fecha><Valor>556,11</Valor></Dolar><Dolar><Fecha>2009-10-07</Fecha><Valor>554,02</Valor></Dolar><Dolar><Fecha>2009-10-08</Fecha><Valor>553,57</Valor></Dolar><Dolar><Fecha>2009-10-09</Fecha><Valor>550,55</Valor></Dolar><Dolar><Fecha>2009-10-13</Fecha><Valor>554,44</Valor></Dolar><Dolar><Fecha>2009-10-14</Fecha><Valor>554,66</Valor></Dolar><Dolar><Fecha>2009-10-15</Fecha><Valor>552,48</Valor></Dolar><Dolar><Fecha>2009-10-16</Fecha><Valor>549,21</Valor></Dolar><Dolar><Fecha>2009-10-19</Fecha><Valor>547,61</Valor></Dolar><Dolar><Fecha>2009-10-20</Fecha><Valor>546,25</Valor></Dolar><Dolar><Fecha>2009-10-21</Fecha><Valor>542,63</Valor></Dolar><Dolar><Fecha>2009-10-22</Fecha><Valor>542,56</Valor></Dolar><Dolar><Fecha>2009-10-23</Fecha><Valor>536,75</Valor></Dolar><Dolar><Fecha>2009-10-26</Fecha><Valor>531,95</Valor></Dolar><Dolar><Fecha>2009-10-27</Fecha><Valor>532,89</Valor></Dolar><Dolar><Fecha>2009-10-28</Fecha><Valor>532,85</Valor></Dolar><Dolar><Fecha>2009-10-29</Fecha><Valor>531,15</Valor></Dolar><Dolar><Fecha>2009-10-30</Fecha><Valor>531,74</Valor></Dolar><Dolar><Fecha>2009-11-02</Fecha><Valor>531,83</Valor></Dolar><Dolar><Fecha>2009-11-03</Fecha><Valor>528,89</Valor></Dolar><Dolar><Fecha>2009-11-04</Fecha><Valor>531,49</Valor></Dolar><Dolar><Fecha>2009-11-05</Fecha><Valor>527,84</Valor></Dolar><Dolar><Fecha>2009-11-06</Fecha><Valor>524,07</Valor></Dolar><Dolar><Fecha>2009-11-09</Fecha><Valor>521,77</Valor></Dolar><Dolar><Fecha>2009-11-10</Fecha><Valor>503,55</Valor></Dolar><Dolar><Fecha>2009-11-11</Fecha><Valor>509,53</Valor></Dolar><Dolar><Fecha>2009-11-12</Fecha><Valor>506,01</Valor></Dolar><Dolar><Fecha>2009-11-13</Fecha><Valor>508,19</Valor></Dolar><Dolar><Fecha>2009-11-16</Fecha><Valor>504,09</Valor></Dolar><Dolar><Fecha>2009-11-17</Fecha><Valor>497,65</Valor></Dolar><Dolar><Fecha>2009-11-18</Fecha><Valor>494,09</Valor></Dolar><Dolar><Fecha>2009-11-19</Fecha><Valor>491,09</Valor></Dolar><Dolar><Fecha>2009-11-20</Fecha><Valor>498,20</Valor></Dolar><Dolar><Fecha>2009-11-23</Fecha><Valor>491,09</Valor></Dolar><Dolar><Fecha>2009-11-24</Fecha><Valor>494,51</Valor></Dolar><Dolar><Fecha>2009-11-25</Fecha><Valor>493,26</Valor></Dolar><Dolar><Fecha>2009-11-26</Fecha><Valor>492,33</Valor></Dolar><Dolar><Fecha>2009-11-27</Fecha><Valor>493,48</Valor></Dolar><Dolar><Fecha>2009-11-30</Fecha><Valor>495,84</Valor></Dolar><Dolar><Fecha>2009-12-01</Fecha><Valor>494,82</Valor></Dolar><Dolar><Fecha>2009-12-02</Fecha><Valor>495,78</Valor></Dolar><Dolar><Fecha>2009-12-03</Fecha><Valor>499,46</Valor></Dolar><Dolar><Fecha>2009-12-04</Fecha><Valor>502,64</Valor></Dolar><Dolar><Fecha>2009-12-07</Fecha><Valor>501,79</Valor></Dolar><Dolar><Fecha>2009-12-09</Fecha><Valor>502,91</Valor></Dolar><Dolar><Fecha>2009-12-10</Fecha><Valor>503,55</Valor></Dolar><Dolar><Fecha>2009-12-11</Fecha><Valor>495,89</Valor></Dolar><Dolar><Fecha>2009-12-14</Fecha><Valor>495,51</Valor></Dolar><Dolar><Fecha>2009-12-15</Fecha><Valor>497,11</Valor></Dolar><Dolar><Fecha>2009-12-16</Fecha><Valor>498,77</Valor></Dolar><Dolar><Fecha>2009-12-17</Fecha><Valor>498,43</Valor></Dolar><Dolar><Fecha>2009-12-18</Fecha><Valor>500,56</Valor></Dolar><Dolar><Fecha>2009-12-21</Fecha><Valor>502,59</Valor></Dolar><Dolar><Fecha>2009-12-22</Fecha><Valor>503,93</Valor></Dolar><Dolar><Fecha>2009-12-23</Fecha><Valor>507,19</Valor></Dolar><Dolar><Fecha>2009-12-24</Fecha><Valor>508,75</Valor></Dolar><Dolar><Fecha>2009-12-28</Fecha><Valor>506,62</Valor></Dolar><Dolar><Fecha>2009-12-29</Fecha><Valor>506,27</Valor></Dolar><Dolar><Fecha>2009-12-30</Fecha><Valor>506,43</Valor></Dolar></Dolares><Euros/><TMCs/><Perfiles/></IndicadoresFinancieros>